MANIFEST.in
README.md
setup.py
videoplayback.mp4
shot_on_iphone/__init__.py
shot_on_iphone/__main__.py
shot_on_iphone/iphone.mp3
shot_on_iphone/iphone.mp4
shot_on_iphone.egg-info/PKG-INFO
shot_on_iphone.egg-info/SOURCES.txt
shot_on_iphone.egg-info/dependency_links.txt
shot_on_iphone.egg-info/requires.txt
shot_on_iphone.egg-info/top_level.txt