Metadata-Version: 2.1
Name: shot-on-iphone
Version: 1.6
Summary: Iphone Meme Maker
Home-page: https://github.com/krypton-byte/shot_on_iphone
Author: Krypton Byte
Author-email: galaxyvplus6434@gmail.com
License: MIT
Download-URL: https://github.com/krypton-byte/shot_on_iphone/archive/1.6.tar.gz
Keywords: Iphone,Meme,generator,Maker
Platform: UNKNOWN
Classifier: Development Status :: 3 - Alpha
Classifier: Intended Audience :: Developers
Classifier: Topic :: Software Development :: Build Tools
Classifier: License :: OSI Approved :: MIT License
Classifier: Programming Language :: Python :: 3.8
Classifier: Programming Language :: Python :: 3.9
